SeqFindr/__init__.py
SeqFindr/blast.py
SeqFindr/config.py
SeqFindr/imaging.py
SeqFindr/SeqFindr
SeqFindr/seqfindr.py
SeqFindr/util.py
SeqFindr/vfdb_to_seqfindr
SeqFindr/vfdb_to_seqfindr.py
SeqFindr-0.35.0.data/data/LICENSE
SeqFindr-0.35.0.data/data/README.rst
SeqFindr-0.35.0.data/data/requirements.txt
SeqFindr-0.35.0.data/data/docs/developer.html
SeqFindr-0.35.0.data/data/docs/genindex.html
SeqFindr-0.35.0.data/data/docs/index.html
SeqFindr-0.35.0.data/data/docs/modules.html
SeqFindr-0.35.0.data/data/docs/objects.inv
SeqFindr-0.35.0.data/data/docs/py-modindex.html
SeqFindr-0.35.0.data/data/docs/search.html
SeqFindr-0.35.0.data/data/docs/searchindex.js
SeqFindr-0.35.0.data/data/docs/SeqFindr.html
SeqFindr-0.35.0.data/data/docs/_sources/developer.txt
SeqFindr-0.35.0.data/data/docs/_sources/index.txt
SeqFindr-0.35.0.data/data/docs/_sources/modules.txt
SeqFindr-0.35.0.data/data/docs/_sources/SeqFindr.txt
SeqFindr-0.35.0.data/data/docs/_static/ajax-loader.gif
SeqFindr-0.35.0.data/data/docs/_static/basic.css
SeqFindr-0.35.0.data/data/docs/_static/comment-bright.png
SeqFindr-0.35.0.data/data/docs/_static/comment-close.png
SeqFindr-0.35.0.data/data/docs/_static/comment.png
SeqFindr-0.35.0.data/data/docs/_static/default.css
SeqFindr-0.35.0.data/data/docs/_static/doctools.js
SeqFindr-0.35.0.data/data/docs/_static/down-pressed.png
SeqFindr-0.35.0.data/data/docs/_static/down.png
SeqFindr-0.35.0.data/data/docs/_static/file.png
SeqFindr-0.35.0.data/data/docs/_static/jquery.js
SeqFindr-0.35.0.data/data/docs/_static/minus.png
SeqFindr-0.35.0.data/data/docs/_static/plus.png
SeqFindr-0.35.0.data/data/docs/_static/pygments.css
SeqFindr-0.35.0.data/data/docs/_static/searchtools.js
SeqFindr-0.35.0.data/data/docs/_static/sidebar.js
SeqFindr-0.35.0.data/data/docs/_static/underscore.js
SeqFindr-0.35.0.data/data/docs/_static/up-pressed.png
SeqFindr-0.35.0.data/data/docs/_static/up.png
SeqFindr-0.35.0.data/data/docs/_static/websupport.js
SeqFindr-0.35.0.dist-info/DESCRIPTION.rst
SeqFindr-0.35.0.dist-info/METADATA
SeqFindr-0.35.0.dist-info/metadata.json
SeqFindr-0.35.0.dist-info/RECORD
SeqFindr-0.35.0.dist-info/top_level.txt
SeqFindr-0.35.0.dist-info/WHEEL
