Metadata-Version: 2.0
Name: SeqFindr
Version: 0.35.0
Summary: A tool to easily create informative genomic feature plots
Home-page: http://github.com/mscook/SeqFindr
Author: Mitchell Stanton-Cook
Author-email: m.stantoncook@gmail.com
License: ECL 2.0
Platform: UNKNOWN
Classifier: Development Status :: 3 - Alpha
Classifier: Environment :: Console
Classifier: Intended Audience :: Science/Research
Classifier: License :: OSI Approved
Classifier: Natural Language :: English
Classifier: Operating System :: POSIX :: Linux
Classifier: Programming Language :: Python
Classifier: Programming Language :: Python :: 2.7
Classifier: Programming Language :: Python :: 2 :: Only
Classifier: Topic :: Scientific/Engineering :: Bio-Informatics
Classifier: Topic :: Scientific/Engineering :: Visualization
Requires-Dist: numpy (==1.8.1)
Requires-Dist: scipy (==0.14.0)
Requires-Dist: matplotlib (==1.3.1)
Requires-Dist: biopython (==1.64)
Requires-Dist: ghalton (==0.6)
